catmass/__init__.py
catmass/catmass_gui.py
catmass/cli.py
catmass/src/__init__.py
catmass/src/__main__.py
catmass/src/functions.py
catmass/src/viewer.py
catmass-0.1.0.dist-info/AUTHORS.rst
catmass-0.1.0.dist-info/LICENSE
catmass-0.1.0.dist-info/METADATA
catmass-0.1.0.dist-info/WHEEL
catmass-0.1.0.dist-info/entry_points.txt
catmass-0.1.0.dist-info/top_level.txt
catmass-0.1.0.dist-info/RECORD
