Metadata-Version: 2.1
Name: catmass
Version: 0.1.0
Summary: Py Qt package for calculating the proper loading of samples for XAS measurements
Home-page: https://github.com/ahoffm02/catmass
Author: Adam S. Hoffman
Author-email: ashoff@slac.stanford.edu
License: GNU General Public License v3
Keywords: catmass
Platform: UNKNOWN
Classifier: Development Status :: 2 - Pre-Alpha
Classifier: Intended Audience :: Developers
Classifier: License :: OSI Approved :: GNU General Public License v3 (GPLv3)
Classifier: Natural Language :: English
Classifier: Programming Language :: Python :: 3
Classifier: Programming Language :: Python :: 3.6
Classifier: Programming Language :: Python :: 3.7
Classifier: Programming Language :: Python :: 3.8
Requires-Python: >=3.6
License-File: LICENSE
License-File: AUTHORS.rst
Requires-Dist: Click (>=7.0)
